DPipe/__init__.py
DPipe/context.py
DemPipe/PipeConfig.json
DemPipe/__init__.py
DemPipe/context.py
DemPipe/action/__init__.py
DemPipe/action/action.py
DemPipe/action/action_base.py
DemPipe/action/context_setter.py
DemPipe/action/procedure.py
DemPipe/action/sequential_pipe.py
DemPipe/action/trigger.py
DemPipe/executor/__init__.py
DemPipe/executor/pipe_exec.py
DemPipe/executor/pipe_exec_base.py
DemPipe/executor/interfaces/__init__.py
DemPipe/executor/interfaces/i_config.py
DemPipe/executor/interfaces/i_mail.py
DemPipe/executor/interfaces/i_notify.py
DemPipe-0.0.2.dist-info/LICENSE
DemPipe-0.0.2.dist-info/METADATA
DemPipe-0.0.2.dist-info/WHEEL
DemPipe-0.0.2.dist-info/top_level.txt
DemPipe-0.0.2.dist-info/RECORD
