Metadata-Version: 2.1
Name: DemPipe
Version: 0.0.2
Summary: A simple Pipeline creator
Home-page: https://github.com/hmiladhia/DemPipe
Author: Dhia Hmila
Author-email: hmiladhia@hotmail.fr
License: UNKNOWN
Platform: UNKNOWN
Classifier: Programming Language :: Python :: 3
Classifier: License :: OSI Approved :: MIT License
Classifier: Operating System :: OS Independent
Requires-Python: >= 3.6
Requires-Dist: configDmanager (>=0.1.8)
Requires-Dist: Dmail (>=0.1.0)
